{
  "2007/08": {
    "Kolkata Knight Riders": [
      "SC Ganguly",
      "BB McCullum",
      "RT Ponting",
      "DJ Hussey",
      "Mohammad Hafeez",
      "WP Saha",
      "LR Shukla",
      "AB Agarkar",
      "M Kartik",
      "I Sharma",
      "DB Das",
      "Salman Butt",
      "BJ Hodge",
      "Umar Gul",
      "AB Dinda",
      "A Chopra",
      "T Taibu",
      "Iqbal Abdulla",
      "Shoaib Akhtar",
      "BAW Mendis"
    ],
    "Royal Challengers Bangalore": [
      "R Dravid",
      "W Jaffer",
      "V Kohli",
      "JH Kallis",
      "CL White",
      "MV Boucher",
      "B Akhil",
      "AA Noffke",
      "P Kumar",
      "Z Khan",
      "SB Joshi",
      "S Chanderpaul",
      "LRPL Taylor",
      "R Vinay Kumar",
      "B Chipli",
      "DW Steyn",
      "Misbah-ul-Haq",
      "DT Patil",
      "A Kumble",
      "J Arunkumar",
      "Abdur Razzak",
      "SP Goswami"
    ],
    "Chennai Super Kings": [
      "PA Patel",
      "ML Hayden",
      "MEK Hussey",
      "MS Dhoni",
      "SK Raina",
      "JDP Oram",
      "S Badrinath",
      "SP Fleming",
      "S Vidyut",
      "JA Morkel",
      "Joginder Sharma",
      "MS Gony",
      "M Muralitharan",
      "M Ntini",
      "S Anirudha",
      "CK Kapugedera",
      "L Balaji",
      "A Mukund",
      "P Amarnath"
    ],
    "Kings XI Punjab": [
      "K Goel",
      "JR Hopes",
      "KC Sangakkara",
      "Yuvraj Singh",
      "SM Katich",
      "IK Pathan",
      "DPMD Jayawardene",
      "S Sohal",
      "B Lee",
      "PP Chawla",
      "WA Mota",
      "RR Sarwan",
      "S Sreesanth",
      "VRV Singh",
      "TM Srivastava",
      "SE Marsh",
      "U Kaul",
      "LA Pomersbach",
      "RR Powar",
      "Gagandeep Singh"
    ],
    "Rajasthan Royals": [
      "T Kohli",
      "YK Pathan",
      "SR Watson",
      "M Kaif",
      "DS Lehmann",
      "RA Jadeja",
      "M Rawat",
      "D Salunkhe",
      "SK Warne",
      "SK Trivedi",
      "Kamran Akmal",
      "GC Smith",
      "Pankaj Singh",
      "SA Asnodkar",
      "Sohail Tanvir",
      "MM Patel",
      "AD Mascarenhas",
      "NK Patel",
      "Younis Khan"
    ],
    "Delhi Daredevils": [
      "G Gambhir",
      "V Sehwag",
      "S Dhawan",
      "Shoaib Malik",
      "MK Tiwary",
      "KD Karthik",
      "R Bhatia",
      "MF Maharoof",
      "VY Mahesh",
      "AB de Villiers",
      "PJ Sangwan",
      "Mohammad Asif",
      "GD McGrath",
      "TM Dilshan",
      "A Mishra",
      "B Geeves",
      "DL Vettori"
    ],
    "Mumbai Indians": [
      "L Ronchi",
      "ST Jayasuriya",
      "DJ Thornely",
      "RV Uthappa",
      "PR Shah",
      "AM Nayar",
      "SM Pollock",
      "Harbhajan Singh",
      "DJ Bravo",
      "MA Khote",
      "A Nehra",
      "SS Tiwary",
      "DS Kulkarni",
      "AM Rahane",
      "MK Pandey",
      "YV Takawale",
      "RR Raje",
      "SR Tendulkar",
      "DR Smith",
      "SD Chitnis",
      "CRD Fernando",
      "VS Yeligati",
      "A Nel"
    ],
    "Deccan Chargers": [
      "AC Gilchrist",
      "Y Venugopal Rao",
      "VVS Laxman",
      "A Symonds",
      "RG Sharma",
      "SB Styris",
      "AS Yadav",
      "SB Bangar",
      "WPUJC Vaas",
      "RP Singh",
      "Shahid Afridi",
      "HH Gibbs",
      "DNT Zoysa",
      "D Kalyankrishna",
      "DB Ravi Teja",
      "PP Ojha",
      "PM Sarvesh Kumar",
      "DP Vijaykumar",
      "LPC Silva",
      "H Das"
    ]
  },
  "2009": {
    "Mumbai Indians": [
      "ST Jayasuriya",
      "SR Tendulkar",
      "S Dhawan",
      "JP Duminy",
      "DJ Bravo",
      "AM Nayar",
      "Harbhajan Singh",
      "Z Khan",
      "PR Shah",
      "SS Tiwary",
      "GR Napier",
      "AM Rahane",
      "RR Raje",
      "DS Kulkarni",
      "L Ronchi",
      "YV Takawale",
      "C Nanda",
      "SL Malinga",
      "Mohammad Ashraful",
      "RA Shaikh"
    ],
    "Chennai Super Kings": [
      "PA Patel",
      "SK Raina",
      "ML Hayden",
      "A Flintoff",
      "MS Dhoni",
      "JDP Oram",
      "S Badrinath",
      "Joginder Sharma",
      "T Thushara",
      "JA Morkel",
      "MS Gony",
      "M Muralitharan",
      "M Vijay",
      "SB Jakati",
      "L Balaji",
      "GJ Bailey",
      "R Ashwin",
      "S Tyagi"
    ],
    "Royal Challengers Bangalore": [
      "JD Ryder",
      "LRPL Taylor",
      "KP Pietersen",
      "RV Uthappa",
      "R Dravid",
      "V Kohli",
      "B Akhil",
      "P Kumar",
      "R Vinay Kumar",
      "JH Kallis",
      "R Bishnoi",
      "DW Steyn",
      "A Kumble",
      "KV Sharma",
      "Pankaj Singh",
      "MV Boucher",
      "SP Goswami",
      "RE van der Merwe",
      "MK Pandey",
      "KP Appanna",
      "W Jaffer",
      "D du Preez",
      "A Mithun"
    ],
    "Rajasthan Royals": [
      "GC Smith",
      "SA Asnodkar",
      "NK Patel",
      "T Henderson",
      "YK Pathan",
      "AD Mascarenhas",
      "RA Jadeja",
      "SK Warne",
      "M Rawat",
      "MM Patel",
      "Kamran Khan",
      "PC Valthaty",
      "RJ Quiney",
      "AS Raut",
      "SK Trivedi",
      "LA Carseldine",
      "NV Ojha",
      "SM Harwood",
      "M Morkel",
      "SD Chitnis",
      "J Botha",
      "A Singh"
    ],
    "Kings XI Punjab": [
      "RS Bopara",
      "K Goel",
      "KC Sangakkara",
      "Yuvraj Singh",
      "DPMD Jayawardene",
      "IK Pathan",
      "T Kohli",
      "PP Chawla",
      "WA Mota",
      "RR Powar",
      "SM Katich",
      "TM Srivastava",
      "S Sohal",
      "S Sreesanth",
      "B Lee",
      "LA Pomersbach",
      "YA Abdulla",
      "VS Malik",
      "VRV Singh",
      "RR Bose"
    ],
    "Delhi Daredevils": [
      "G Gambhir",
      "V Sehwag",
      "AB de Villiers",
      "TM Dilshan",
      "KD Karthik",
      "MK Tiwary",
      "M Manhas",
      "DL Vettori",
      "A Mishra",
      "PJ Sangwan",
      "DA Warner",
      "R Bhatia",
      "MF Maharoof",
      "A Nehra",
      "AB McDonald",
      "Y Nagar",
      "DP Nannes",
      "AM Salvi",
      "VY Mahesh"
    ],
    "Kolkata Knight Riders": [
      "BB McCullum",
      "CH Gayle",
      "SC Ganguly",
      "BJ Hodge",
      "A Chopra",
      "LR Shukla",
      "MC Henriques",
      "AB Agarkar",
      "M Kartik",
      "I Sharma",
      "AB Dinda",
      "SB Bangar",
      "Yashpal Singh",
      "AN Ghosh",
      "BAW Mendis",
      "MN van Wyk",
      "WP Saha",
      "DJ Hussey",
      "AD Mathews",
      "Mashrafe Mortaza",
      "SS Shaikh",
      "Anureet Singh",
      "SS Sarkar",
      "CK Langeveldt"
    ],
    "Deccan Chargers": [
      "AC Gilchrist",
      "HH Gibbs",
      "VVS Laxman",
      "RG Sharma",
      "SB Styris",
      "Y Venugopal Rao",
      "DB Ravi Teja",
      "FH Edwards",
      "DR Smith",
      "RP Singh",
      "PP Ojha",
      "AA Bilakhia",
      "TL Suman",
      "Shoaib Ahmed",
      "RJ Harris",
      "A Symonds",
      "WPUJC Vaas",
      "Harmeet Singh",
      "Jaskaran Singh"
    ]
  },
  "2009/10": {
    "Kolkata Knight Riders": [
      "MK Tiwary",
      "SC Ganguly",
      "CA Pujara",
      "BJ Hodge",
      "OA Shah",
      "AD Mathews",
      "WP Saha",
      "LR Shukla",
      "RS Gavaskar",
      "SE Bond",
      "M Kartik",
      "I Sharma",
      "CH Gayle",
      "Mandeep Singh",
      "DJ Hussey",
      "AB Agarkar",
      "CK Langeveldt",
      "BB McCullum",
      "AB Dinda",
      "BAW Mendis",
      "Iqbal Abdulla",
      "MB Parmar",
      "JD Unadkat"
    ],
    "Deccan Chargers": [
      "AC Gilchrist",
      "VVS Laxman",
      "HH Gibbs",
      "A Symonds",
      "RG Sharma",
      "Anirudh Singh",
      "TL Suman",
      "WPUJC Vaas",
      "Jaskaran Singh",
      "RP Singh",
      "MD Mishra",
      "Y Venugopal Rao",
      "R Sharma",
      "KAJ Roach",
      "RJ Harris",
      "PP Ojha",
      "DR Smith",
      "AA Bilakhia",
      "B Sumanth",
      "MR Marsh",
      "Harmeet Singh"
    ],
    "Mumbai Indians": [
      "ST Jayasuriya",
      "SR Tendulkar",
      "AP Tare",
      "SS Tiwary",
      "AT Rayudu",
      "R Sathish",
      "Harbhajan Singh",
      "R McLaren",
      "KA Pollard",
      "DJ Bravo",
      "Z Khan",
      "S Dhawan",
      "AN Ahmed",
      "JP Duminy",
      "C Madan",
      "AM Nayar",
      "STR Binny",
      "CRD Fernando",
      "SL Malinga",
      "AG Murtaza",
      "DS Kulkarni"
    ],
    "Rajasthan Royals": [
      "GC Smith",
      "NV Ojha",
      "AA Jhunjhunwala",
      "YK Pathan",
      "P Dogra",
      "AD Mascarenhas",
      "A Uniyal",
      "SK Warne",
      "SA Asnodkar",
      "MJ Lumb",
      "DR Martyn",
      "S Narwal",
      "M Morkel",
      "MM Patel",
      "SK Trivedi",
      "FY Fazal",
      "AC Voges",
      "SW Tait",
      "SR Watson",
      "AS Raut",
      "AP Dole",
      "AG Paunikar",
      "AJ Finch",
      "Kamran Khan",
      "SB Wagh"
    ],
    "Kings XI Punjab": [
      "RS Bopara",
      "MS Bisla",
      "KC Sangakkara",
      "Yuvraj Singh",
      "DPMD Jayawardene",
      "IK Pathan",
      "M Kaif",
      "PP Chawla",
      "RR Powar",
      "S Sreesanth",
      "YA Abdulla",
      "AB Barath",
      "Bipul Sharma",
      "J Theron",
      "SJ Srivastava",
      "K Goel",
      "B Lee",
      "SE Marsh",
      "VS Malik",
      "RS Sodhi",
      "L Ablish",
      "VRV Singh"
    ],
    "Delhi Daredevils": [
      "G Gambhir",
      "V Sehwag",
      "TM Dilshan",
      "AB de Villiers",
      "KD Karthik",
      "M Manhas",
      "MF Maharoof",
      "A Mishra",
      "PJ Sangwan",
      "S Ladda",
      "DP Nannes",
      "DA Warner",
      "R Bhatia",
      "MC Henriques",
      "Y Nagar",
      "UT Yadav",
      "KM Jadhav",
      "AB McDonald",
      "PD Collingwood",
      "DL Vettori",
      "A Nehra",
      "VY Mahesh"
    ],
    "Royal Challengers Bangalore": [
      "JH Kallis",
      "SP Goswami",
      "MK Pandey",
      "V Kohli",
      "EJG Morgan",
      "R Dravid",
      "RV Uthappa",
      "RE van der Merwe",
      "P Kumar",
      "MV Boucher",
      "R Vinay Kumar",
      "DW Steyn",
      "A Kumble",
      "KP Pietersen",
      "CL White",
      "LRPL Taylor",
      "A Mithun",
      "KP Appanna",
      "S Sriram",
      "Pankaj Singh",
      "ND Doshi",
      "B Akhil"
    ],
    "Chennai Super Kings": [
      "M Vijay",
      "ML Hayden",
      "SK Raina",
      "S Badrinath",
      "JM Kemp",
      "MS Dhoni",
      "JA Morkel",
      "R Ashwin",
      "L Balaji",
      "M Muralitharan",
      "S Tyagi",
      "PA Patel",
      "MS Gony",
      "GJ Bailey",
      "KB Arun Karthik",
      "T Thushara",
      "MEK Hussey",
      "DE Bollinger",
      "S Anirudha",
      "Joginder Sharma",
      "SB Jakati",
      "NLTC Perera",
      "C Ganapathy"
    ]
  },
  "2011": {
    "Chennai Super Kings": [
      "S Anirudha",
      "M Vijay",
      "SK Raina",
      "MS Dhoni",
      "JA Morkel",
      "SB Styris",
      "S Badrinath",
      "MEK Hussey",
      "R Ashwin",
      "Joginder Sharma",
      "S Randiv",
      "DE Bollinger",
      "WP Saha",
      "DJ Bravo",
      "TG Southee",
      "SB Jakati",
      "KMDN Kulasekara"
    ],
    "Kolkata Knight Riders": [
      "MS Bisla",
      "JH Kallis",
      "YK Pathan",
      "MK Tiwary",
      "EJG Morgan",
      "G Gambhir",
      "LR Shukla",
      "Iqbal Abdulla",
      "R Bhatia",
      "Shakib Al Hasan",
      "B Lee",
      "L Balaji",
      "BJ Haddin",
      "SP Goswami",
      "RN ten Doeschate",
      "MV Boucher",
      "S Ladda",
      "JD Unadkat"
    ],
    "Deccan Chargers": [
      "S Dhawan",
      "IR Jaggi",
      "KC Sangakkara",
      "B Chipli",
      "JP Duminy",
      "DT Christian",
      "DB Ravi Teja",
      "DW Steyn",
      "A Mishra",
      "I Sharma",
      "S Sohal",
      "MS Gony",
      "CL White",
      "I Malhotra",
      "MJ Lumb",
      "PP Ojha",
      "Harmeet Singh",
      "Anand Rajan"
    ],
    "Rajasthan Royals": [
      "AG Paunikar",
      "R Dravid",
      "J Botha",
      "LRPL Taylor",
      "AL Menaria",
      "AM Rahane",
      "SR Watson",
      "FY Fazal",
      "AS Raut",
      "SK Warne",
      "A Singh",
      "SW Tait",
      "SK Trivedi",
      "SA Asnodkar",
      "STR Binny",
      "DH Yagnik",
      "PR Shah",
      "JDP Oram",
      "AA Chavan",
      "ND Doshi",
      "Pankaj Singh"
    ],
    "Kochi Tuskers Kerala": [
      "BB McCullum",
      "VVS Laxman",
      "DPMD Jayawardene",
      "BJ Hodge",
      "RA Jadeja",
      "RV Gomez",
      "PA Patel",
      "R Vinay Kumar",
      "S Sreesanth",
      "RP Singh",
      "KM Jadhav",
      "RR Powar",
      "NLTC Perera",
      "M Muralitharan",
      "M Klinger",
      "B Akhil",
      "P Parameswaran",
      "OA Shah",
      "Y Gnaneswara Rao",
      "P Prasanth"
    ],
    "Royal Challengers Bangalore": [
      "MA Agarwal",
      "TM Dilshan",
      "V Kohli",
      "AB de Villiers",
      "SS Tiwary",
      "AUK Pathan",
      "Z Khan",
      "CA Pujara",
      "JJ van der Wath",
      "R Ninan",
      "DL Vettori",
      "S Aravind",
      "CH Gayle",
      "A Mithun",
      "J Syed Mohammad",
      "M Kaif",
      "LA Pomersbach",
      "KB Arun Karthik",
      "CK Langeveldt",
      "DP Nannes",
      "AA Kazi"
    ],
    "Delhi Daredevils": [
      "DA Warner",
      "V Sehwag",
      "UBT Chand",
      "AJ Finch",
      "NV Ojha",
      "Y Venugopal Rao",
      "IK Pathan",
      "RE van der Merwe",
      "M Morkel",
      "UT Yadav",
      "AB Dinda",
      "MS Wade",
      "JR Hopes",
      "Y Nagar",
      "TR Birt",
      "CA Ingram",
      "AB Agarkar",
      "S Nadeem",
      "AB McDonald",
      "S Sriram",
      "VR Aaron",
      "AM Salvi"
    ],
    "Mumbai Indians": [
      "DJ Jacobs",
      "SR Tendulkar",
      "AT Rayudu",
      "RG Sharma",
      "JEC Franklin",
      "A Symonds",
      "R Sathish",
      "KA Pollard",
      "Harbhajan Singh",
      "SL Malinga",
      "AG Murtaza",
      "AC Blizzard",
      "TL Suman",
      "DS Kulkarni",
      "MM Patel",
      "AN Ahmed",
      "RW Price"
    ],
    "Kings XI Punjab": [
      "AC Gilchrist",
      "SE Marsh",
      "PC Valthaty",
      "KD Karthik",
      "AM Nayar",
      "Sunny Singh",
      "R McLaren",
      "PP Chawla",
      "P Kumar",
      "NJ Rimmington",
      "DJ Hussey",
      "RJ Harris",
      "Bipul Sharma",
      "L Ablish",
      "Mandeep Singh",
      "SD Chitnis",
      "SJ Srivastava",
      "BA Bhatt",
      "VS Malik"
    ],
    "Pune Warriors": [
      "GC Smith",
      "M Manhas",
      "JD Ryder",
      "RV Uthappa",
      "Yuvraj Singh",
      "MD Mishra",
      "WD Parnell",
      "R Sharma",
      "TD Paine",
      "M Kartik",
      "SB Wagh",
      "AC Thomas",
      "MK Pandey",
      "NL McCullum",
      "JE Taylor",
      "MR Marsh",
      "Harpreet Singh",
      "AA Jhunjhunwala",
      "CJ Ferguson",
      "SC Ganguly",
      "B Kumar",
      "S Rana",
      "Kamran Khan",
      "JP Faulkner",
      "SS Mundhe"
    ]
  },
  "2012": {
    "Chennai Super Kings": [
      "F du Plessis",
      "M Vijay",
      "SK Raina",
      "DJ Bravo",
      "JA Morkel",
      "S Badrinath",
      "MS Dhoni",
      "RA Jadeja",
      "R Ashwin",
      "SB Jakati",
      "DE Bollinger",
      "WP Saha",
      "KMDN Kulasekara",
      "MEK Hussey",
      "S Anirudha",
      "VY Mahesh",
      "BW Hilfenhaus"
    ],
    "Mumbai Indians": [
      "RE Levi",
      "SR Tendulkar",
      "RG Sharma",
      "AT Rayudu",
      "JEC Franklin",
      "KD Karthik",
      "SA Yadav",
      "KA Pollard",
      "Harbhajan Singh",
      "SL Malinga",
      "PP Ojha",
      "MM Patel",
      "TL Suman",
      "DJ Jacobs",
      "CJ McKay",
      "RP Singh",
      "NLTC Perera",
      "RJ Peterson",
      "AC Blizzard",
      "DR Smith",
      "HH Gibbs",
      "DS Kulkarni",
      "AN Ahmed",
      "R Shukla"
    ],
    "Kolkata Knight Riders": [
      "BB McCullum",
      "JH Kallis",
      "G Gambhir",
      "MK Tiwary",
      "YK Pathan",
      "DB Das",
      "LR Shukla",
      "R Bhatia",
      "B Lee",
      "Iqbal Abdulla",
      "SP Narine",
      "MS Bisla",
      "RN ten Doeschate",
      "Shakib Al Hasan",
      "M de Lange",
      "L Balaji",
      "JD Unadkat",
      "PJ Sangwan"
    ],
    "Delhi Daredevils": [
      "AJ Finch",
      "V Sehwag",
      "IK Pathan",
      "GJ Maxwell",
      "NV Ojha",
      "Y Venugopal Rao",
      "Y Nagar",
      "DAJ Bracewell",
      "M Morkel",
      "KP Pietersen",
      "DPMD Jayawardene",
      "LRPL Taylor",
      "P Negi",
      "DA Warner",
      "S Nadeem",
      "VR Aaron",
      "UBT Chand",
      "AD Russell",
      "UT Yadav",
      "Sunny Gupta",
      "RE van der Merwe",
      "AB Agarkar"
    ],
    "Pune Warriors": [
      "MK Pandey",
      "WD Parnell",
      "SC Ganguly",
      "RV Uthappa",
      "CJ Ferguson",
      "SPD Smith",
      "MN Samuels",
      "B Kumar",
      "M Kartik",
      "JD Ryder",
      "R Sharma",
      "AD Mathews",
      "M Manhas",
      "A Nehra",
      "AB Dinda",
      "AC Thomas",
      "MJ Clarke",
      "AP Majumdar",
      "MD Mishra",
      "K Upadhyay",
      "Harpreet Singh",
      "AG Murtaza",
      "LJ Wright"
    ],
    "Rajasthan Royals": [
      "R Dravid",
      "AM Rahane",
      "AL Menaria",
      "BJ Hodge",
      "OA Shah",
      "KK Cooper",
      "SP Goswami",
      "J Botha",
      "AA Chavan",
      "A Singh",
      "SK Trivedi",
      "GB Hogg",
      "DH Yagnik",
      "STR Binny",
      "SR Watson",
      "A Chandila",
      "Pankaj Singh",
      "SW Tait"
    ],
    "Kings XI Punjab": [
      "AC Gilchrist",
      "PC Valthaty",
      "SE Marsh",
      "AM Nayar",
      "Mandeep Singh",
      "DJ Hussey",
      "Bipul Sharma",
      "PP Chawla",
      "JP Faulkner",
      "P Kumar",
      "Harmeet Singh",
      "AD Mascarenhas",
      "P Dogra",
      "BA Bhatt",
      "N Saini",
      "DA Miller",
      "Azhar Mahmood",
      "Gurkeerat Singh",
      "RJ Harris",
      "SD Chitnis",
      "P Awana",
      "RR Powar"
    ],
    "Royal Challengers Bangalore": [
      "AB McDonald",
      "CA Pujara",
      "V Kohli",
      "AB de Villiers",
      "SS Tiwary",
      "MA Agarwal",
      "DL Vettori",
      "R Vinay Kumar",
      "HV Patel",
      "CH Gayle",
      "Z Khan",
      "RR Bhatkal",
      "M Kaif",
      "S Aravind",
      "M Muralitharan",
      "TM Dilshan",
      "AUK Pathan",
      "J Syed Mohammad",
      "P Parameswaran",
      "KP Appanna",
      "A Mithun"
    ],
    "Deccan Chargers": [
      "DJ Harris",
      "S Dhawan",
      "PA Patel",
      "CL White",
      "B Chipli",
      "DT Christian",
      "MS Gony",
      "DB Ravi Teja",
      "DW Steyn",
      "Ankit Sharma",
      "KC Sangakkara",
      "A Mishra",
      "JP Duminy",
      "AA Jhunjhunwala",
      "IR Jaggi",
      "A Ashish Reddy",
      "V Pratap Singh",
      "BB Samantray",
      "PA Reddy",
      "J Theron",
      "CA Lynn",
      "TP Sudhindra",
      "Anand Rajan"
    ]
  },
  "2013": {
    "Delhi Daredevils": [
      "UBT Chand",
      "DPMD Jayawardene",
      "DA Warner",
      "MC Juneja",
      "NV Ojha",
      "J Botha",
      "IK Pathan",
      "AD Russell",
      "S Nadeem",
      "A Nehra",
      "BMAJ Mendis",
      "KM Jadhav",
      "M Morkel",
      "UT Yadav",
      "V Sehwag",
      "BJ Rohrer",
      "AB Agarkar",
      "RE van der Merwe",
      "CM Gautam",
      "S Kaul",
      "B Chipli",
      "P Negi"
    ],
    "Kolkata Knight Riders": [
      "MS Bisla",
      "G Gambhir",
      "JH Kallis",
      "MK Tiwary",
      "EJG Morgan",
      "YK Pathan",
      "LR Shukla",
      "R Bhatia",
      "B Lee",
      "Mohammed Shami",
      "SP Narine",
      "R McLaren",
      "PJ Sangwan",
      "DB Das",
      "SMSM Senanayake",
      "L Balaji",
      "BB McCullum",
      "S Narwal",
      "Iqbal Abdulla",
      "RN ten Doeschate",
      "P Dogra",
      "S Ladda"
    ],
    "Royal Challengers Bangalore": [
      "CH Gayle",
      "TM Dilshan",
      "V Kohli",
      "MA Agarwal",
      "DT Christian",
      "KK Nair",
      "KB Arun Karthik",
      "MC Henriques",
      "R Vinay Kumar",
      "M Kartik",
      "JD Unadkat",
      "AB de Villiers",
      "R Rampaul",
      "KL Rahul",
      "AB McDonald",
      "J Syed Mohammad",
      "SS Tiwary",
      "A Mukund",
      "CA Pujara",
      "A Mithun",
      "M Muralitharan",
      "RP Singh",
      "Z Khan"
    ],
    "Mumbai Indians": [
      "RT Ponting",
      "SR Tendulkar",
      "KD Karthik",
      "RG Sharma",
      "AT Rayudu",
      "Harbhajan Singh",
      "KA Pollard",
      "DR Smith",
      "R Dhawan",
      "MG Johnson",
      "SL Malinga",
      "PP Ojha",
      "GJ Maxwell",
      "AP Tare",
      "NM Coulter-Nile",
      "MM Patel",
      "JJ Bumrah",
      "JDP Oram",
      "YS Chahal",
      "DS Kulkarni",
      "P Suyal",
      "AN Ahmed"
    ],
    "Sunrisers Hyderabad": [
      "PA Reddy",
      "PA Patel",
      "KC Sangakkara",
      "CL White",
      "NLTC Perera",
      "GH Vihari",
      "A Ashish Reddy",
      "DB Ravi Teja",
      "DW Steyn",
      "BB Samantray",
      "A Mishra",
      "KV Sharma",
      "Q de Kock",
      "S Dhawan",
      "X Thalaivan Sargunam",
      "DJG Sammy",
      "I Sharma",
      "Ankit Sharma",
      "Anand Rajan"
    ],
    "Pune Warriors": [
      "RV Uthappa",
      "MK Pandey",
      "MN Samuels",
      "Yuvraj Singh",
      "LRPL Taylor",
      "AM Nayar",
      "MR Marsh",
      "AD Mathews",
      "B Kumar",
      "R Sharma",
      "AB Dinda",
      "TL Suman",
      "AJ Finch",
      "SPD Smith",
      "LJ Wright",
      "M Manhas",
      "AG Murtaza",
      "IC Pandey",
      "KW Richardson",
      "BAW Mendis",
      "UA Birla",
      "M Rawat",
      "WD Parnell",
      "Parvez Rasool",
      "K Upadhyay",
      "RV Gomez"
    ],
    "Rajasthan Royals": [
      "MDKJ Perera",
      "AM Rahane",
      "R Dravid",
      "STR Binny",
      "BJ Hodge",
      "AL Menaria",
      "KK Cooper",
      "R Shukla",
      "SR Watson",
      "DH Yagnik",
      "S Sreesanth",
      "JP Faulkner",
      "SV Samson",
      "A Chandila",
      "SW Tait",
      "SK Trivedi",
      "OA Shah",
      "Sachin Baby",
      "PV Tambe",
      "S Badree",
      "Harmeet Singh",
      "AA Chavan",
      "GB Hogg",
      "VS Malik"
    ],
    "Chennai Super Kings": [
      "MEK Hussey",
      "M Vijay",
      "SK Raina",
      "DJ Bravo",
      "S Badrinath",
      "MS Dhoni",
      "RA Jadeja",
      "R Ashwin",
      "B Laughlin",
      "AS Rajpoot",
      "CH Morris",
      "S Anirudha",
      "JA Morkel",
      "WP Saha",
      "MM Sharma",
      "DP Nannes",
      "JO Holder"
    ],
    "Kings XI Punjab": [
      "AC Gilchrist",
      "Mandeep Singh",
      "M Vohra",
      "DJ Hussey",
      "Gurkeerat Singh",
      "Azhar Mahmood",
      "R Sathish",
      "PP Chawla",
      "RJ Harris",
      "P Kumar",
      "P Awana",
      "DA Miller",
      "MS Gony",
      "PC Valthaty",
      "AD Mascarenhas",
      "LA Pomersbach",
      "SE Marsh",
      "Harmeet Singh",
      "Sandeep Sharma",
      "BA Bhatt",
      "MG Neser",
      "Bipul Sharma"
    ]
  },
  "2014": {
    "Kolkata Knight Riders": [
      "G Gambhir",
      "JH Kallis",
      "MK Pandey",
      "RV Uthappa",
      "YK Pathan",
      "Shakib Al Hasan",
      "SA Yadav",
      "CA Lynn",
      "R Vinay Kumar",
      "PP Chawla",
      "SP Narine",
      "UT Yadav",
      "M Morkel",
      "MS Bisla",
      "AD Russell",
      "RN ten Doeschate",
      "PJ Cummins"
    ],
    "Mumbai Indians": [
      "MEK Hussey",
      "AP Tare",
      "AT Rayudu",
      "RG Sharma",
      "KA Pollard",
      "CJ Anderson",
      "Harbhajan Singh",
      "CM Gautam",
      "Z Khan",
      "SL Malinga",
      "PP Ojha",
      "JJ Bumrah",
      "BR Dunk",
      "LMP Simmons",
      "S Gopal",
      "M de Lange",
      "P Kumar",
      "P Suyal",
      "K Santokie"
    ],
    "Delhi Daredevils": [
      "MA Agarwal",
      "M Vijay",
      "KD Karthik",
      "MK Tiwary",
      "JP Duminy",
      "LRPL Taylor",
      "JDS Neesham",
      "S Nadeem",
      "Mohammed Shami",
      "JD Unadkat",
      "Q de Kock",
      "KP Pietersen",
      "KM Jadhav",
      "LR Shukla",
      "R Shukla",
      "Imran Tahir",
      "S Kaul",
      "WD Parnell",
      "R Sharma",
      "NM Coulter-Nile"
    ],
    "Royal Challengers Bangalore": [
      "PA Patel",
      "NJ Maddinson",
      "V Kohli",
      "Yuvraj Singh",
      "AB de Villiers",
      "YV Takawale",
      "JA Morkel",
      "S Rana",
      "MA Starc",
      "R Rampaul",
      "AB Dinda",
      "CH Gayle",
      "VR Aaron",
      "RR Rossouw",
      "HV Patel",
      "YS Chahal",
      "VH Zol",
      "AN Ahmed",
      "M Muralitharan",
      "SB Jakati"
    ],
    "Chennai Super Kings": [
      "DR Smith",
      "BB McCullum",
      "SK Raina",
      "MS Dhoni",
      "DJ Bravo",
      "F du Plessis",
      "RA Jadeja",
      "M Manhas",
      "R Ashwin",
      "DJ Hussey",
      "MM Sharma",
      "A Nehra",
      "P Negi",
      "IC Pandey",
      "BW Hilfenhaus",
      "S Badree",
      "V Shankar",
      "JW Hastings"
    ],
    "Kings XI Punjab": [
      "CA Pujara",
      "V Sehwag",
      "GJ Maxwell",
      "AR Patel",
      "DA Miller",
      "GJ Bailey",
      "WP Saha",
      "MG Johnson",
      "R Dhawan",
      "L Balaji",
      "Sandeep Sharma",
      "Mandeep Singh",
      "Shivam Sharma",
      "M Vohra",
      "SE Marsh",
      "BE Hendricks",
      "Karanveer Singh",
      "P Awana",
      "M Kartik"
    ],
    "Sunrisers Hyderabad": [
      "AJ Finch",
      "DA Warner",
      "S Dhawan",
      "KL Rahul",
      "DJG Sammy",
      "Y Venugopal Rao",
      "KV Sharma",
      "IK Pathan",
      "DW Steyn",
      "A Mishra",
      "B Kumar",
      "NV Ojha",
      "MC Henriques",
      "S Anirudha",
      "JO Holder",
      "I Sharma",
      "Parvez Rasool"
    ],
    "Rajasthan Royals": [
      "AM Nayar",
      "SV Samson",
      "AM Rahane",
      "SR Watson",
      "STR Binny",
      "BJ Hodge",
      "R Bhatia",
      "JP Faulkner",
      "SPD Smith",
      "TG Southee",
      "DS Kulkarni",
      "PV Tambe",
      "KK Nair",
      "KW Richardson",
      "Ankit Sharma",
      "DH Yagnik",
      "KK Cooper",
      "BCJ Cutting",
      "UBT Chand",
      "R Tewatia",
      "VS Malik",
      "Iqbal Abdulla"
    ]
  },
  "2015": {
    "Mumbai Indians": [
      "RG Sharma",
      "AJ Finch",
      "AP Tare",
      "AT Rayudu",
      "CJ Anderson",
      "KA Pollard",
      "J Suchith",
      "Harbhajan Singh",
      "PA Patel",
      "UBT Chand",
      "S Gopal",
      "LMP Simmons",
      "R Vinay Kumar",
      "HH Pandya",
      "MJ McClenaghan",
      "SL Malinga",
      "JJ Bumrah",
      "PP Ojha",
      "P Suyal",
      "M de Lange"
    ],
    "Kolkata Knight Riders": [
      "RV Uthappa",
      "G Gambhir",
      "MK Pandey",
      "SA Yadav",
      "YK Pathan",
      "AD Russell",
      "Shakib Al Hasan",
      "RN ten Doeschate",
      "PP Chawla",
      "PJ Cummins",
      "UT Yadav",
      "GB Hogg",
      "J Botha",
      "SP Narine",
      "Azhar Mahmood",
      "M Morkel",
      "KC Cariappa"
    ],
    "Chennai Super Kings": [
      "DR Smith",
      "BB McCullum",
      "SK Raina",
      "F du Plessis",
      "RA Jadeja",
      "MS Dhoni",
      "DJ Bravo",
      "R Ashwin",
      "MM Sharma",
      "A Nehra",
      "P Negi",
      "RG More",
      "MEK Hussey",
      "IC Pandey"
    ],
    "Delhi Daredevils": [
      "MA Agarwal",
      "CM Gautam",
      "JA Morkel",
      "SS Iyer",
      "KM Jadhav",
      "Yuvraj Singh",
      "JP Duminy",
      "NM Coulter-Nile",
      "A Mishra",
      "Imran Tahir",
      "AD Mathews",
      "MK Tiwary",
      "S Nadeem",
      "DJ Muthuswami",
      "SS Tiwary",
      "Q de Kock",
      "JD Unadkat",
      "Z Khan",
      "GS Sandhu",
      "J Yadav"
    ],
    "Rajasthan Royals": [
      "AM Rahane",
      "SV Samson",
      "SPD Smith",
      "KK Nair",
      "STR Binny",
      "JP Faulkner",
      "DJ Hooda",
      "CH Morris",
      "TG Southee",
      "SR Watson",
      "DS Kulkarni",
      "PV Tambe",
      "J Theron",
      "R Bhatia",
      "Ankit Sharma",
      "R Tewatia",
      "BB Sran"
    ],
    "Kings XI Punjab": [
      "V Sehwag",
      "WP Saha",
      "M Vijay",
      "GJ Maxwell",
      "AR Patel",
      "DA Miller",
      "GJ Bailey",
      "MG Johnson",
      "Anureet Singh",
      "Karanveer Singh",
      "R Dhawan",
      "NLTC Perera",
      "Gurkeerat Singh",
      "SE Marsh",
      "Sandeep Sharma",
      "M Vohra",
      "SN Thakur",
      "BE Hendricks",
      "Shivam Sharma"
    ],
    "Sunrisers Hyderabad": [
      "DA Warner",
      "S Dhawan",
      "KL Rahul",
      "NV Ojha",
      "RS Bopara",
      "KS Williamson",
      "KV Sharma",
      "Parvez Rasool",
      "EJG Morgan",
      "A Ashish Reddy",
      "P Kumar",
      "MC Henriques",
      "GH Vihari",
      "DW Steyn",
      "B Kumar",
      "Bipul Sharma",
      "TA Boult",
      "I Sharma"
    ],
    "Royal Challengers Bangalore": [
      "CH Gayle",
      "V Kohli",
      "KD Karthik",
      "Mandeep Singh",
      "AB de Villiers",
      "DJG Sammy",
      "SA Abbott",
      "HV Patel",
      "AN Ahmed",
      "VR Aaron",
      "YS Chahal",
      "MS Bisla",
      "RR Rossouw",
      "D Wiese",
      "Iqbal Abdulla",
      "SN Khan",
      "MA Starc",
      "NJ Maddinson",
      "S Aravind",
      "AB Dinda"
    ]
  },
  "2016": {
    "Mumbai Indians": [
      "LMP Simmons",
      "RG Sharma",
      "HH Pandya",
      "JC Buttler",
      "AT Rayudu",
      "KA Pollard",
      "S Gopal",
      "Harbhajan Singh",
      "R Vinay Kumar",
      "MJ McClenaghan",
      "PA Patel",
      "KH Pandya",
      "TG Southee",
      "MJ Guptill",
      "JJ Bumrah",
      "N Rana",
      "UBT Chand",
      "J Suchith"
    ],
    "Rising Pune Supergiants": [
      "AM Rahane",
      "F du Plessis",
      "KP Pietersen",
      "SPD Smith",
      "MS Dhoni",
      "MR Marsh",
      "R Bhatia",
      "NLTC Perera",
      "IK Pathan",
      "R Ashwin",
      "Ankit Sharma",
      "M Ashwin",
      "JA Morkel",
      "SS Tiwary",
      "PSP Handscomb",
      "UT Khawaja",
      "GJ Bailey",
      "A Zampa",
      "RP Singh",
      "I Sharma",
      "AB Dinda",
      "SM Boland",
      "DL Chahar"
    ],
    "Delhi Daredevils": [
      "MA Agarwal",
      "Q de Kock",
      "SS Iyer",
      "KK Nair",
      "SV Samson",
      "P Negi",
      "CR Brathwaite",
      "CH Morris",
      "NM Coulter-Nile",
      "A Mishra",
      "Z Khan",
      "JP Duminy",
      "RR Pant",
      "SW Billings",
      "Mohammed Shami",
      "J Yadav",
      "S Nadeem",
      "Imran Tahir"
    ],
    "Kolkata Knight Riders": [
      "RV Uthappa",
      "G Gambhir",
      "MK Pandey",
      "AD Russell",
      "YK Pathan",
      "C Munro",
      "SA Yadav",
      "Shakib Al Hasan",
      "R Sathish",
      "PP Chawla",
      "UT Yadav",
      "CA Lynn",
      "JO Holder",
      "SP Narine",
      "M Morkel",
      "JW Hastings",
      "GB Hogg",
      "Kuldeep Yadav",
      "JD Unadkat",
      "AS Rajpoot"
    ],
    "Kings XI Punjab": [
      "M Vijay",
      "M Vohra",
      "DA Miller",
      "GJ Maxwell",
      "WP Saha",
      "MP Stoinis",
      "AR Patel",
      "SE Marsh",
      "MG Johnson",
      "MM Sharma",
      "P Sahu",
      "Sandeep Sharma",
      "KJ Abbott",
      "NS Naik",
      "R Dhawan",
      "Gurkeerat Singh",
      "KC Cariappa",
      "Swapnil Singh",
      "HM Amla",
      "F Behardien",
      "Anureet Singh"
    ],
    "Gujarat Lions": [
      "AJ Finch",
      "BB McCullum",
      "SK Raina",
      "KD Karthik",
      "RA Jadeja",
      "Ishan Kishan",
      "DJ Bravo",
      "AD Nath",
      "JP Faulkner",
      "P Kumar",
      "DS Kulkarni",
      "DW Steyn",
      "DR Smith",
      "PV Tambe",
      "S Kaushik",
      "ER Dwivedi",
      "SB Jakati",
      "PJ Sangwan",
      "S Ladda"
    ],
    "Royal Challengers Bangalore": [
      "CH Gayle",
      "V Kohli",
      "AB de Villiers",
      "SR Watson",
      "KM Jadhav",
      "SN Khan",
      "D Wiese",
      "KL Rahul",
      "TM Head",
      "STR Binny",
      "KW Richardson",
      "Sachin Baby",
      "Parvez Rasool",
      "Iqbal Abdulla",
      "CJ Jordan",
      "AF Milne",
      "HV Patel",
      "YS Chahal",
      "S Aravind",
      "VR Aaron",
      "T Shamsi"
    ],
    "Sunrisers Hyderabad": [
      "DA Warner",
      "S Dhawan",
      "MC Henriques",
      "NV Ojha",
      "DJ Hooda",
      "EJG Morgan",
      "A Ashish Reddy",
      "KV Sharma",
      "B Kumar",
      "AP Tare",
      "Bipul Sharma",
      "KS Williamson",
      "Yuvraj Singh",
      "BB Sran",
      "A Nehra",
      "BCJ Cutting",
      "Mustafizur Rahman",
      "TA Boult"
    ]
  },
  "2017": {
    "Sunrisers Hyderabad": [
      "DA Warner",
      "S Dhawan",
      "MC Henriques",
      "Yuvraj Singh",
      "DJ Hooda",
      "BCJ Cutting",
      "NV Ojha",
      "V Shankar",
      "Rashid Khan",
      "B Kumar",
      "Bipul Sharma",
      "Mohammad Nabi",
      "KS Williamson",
      "S Kaul",
      "CJ Jordan",
      "A Nehra",
      "Mustafizur Rahman",
      "BB Sran",
      "Mohammed Siraj"
    ],
    "Royal Challengers Bangalore": [
      "CH Gayle",
      "Mandeep Singh",
      "TM Head",
      "KM Jadhav",
      "SR Watson",
      "Sachin Baby",
      "STR Binny",
      "S Aravind",
      "YS Chahal",
      "TS Mills",
      "A Choudhary",
      "Vishnu Vinod",
      "Iqbal Abdulla",
      "P Negi",
      "AB de Villiers",
      "V Kohli",
      "AF Milne",
      "S Badree",
      "B Stanlake",
      "Avesh Khan",
      "HV Patel"
    ],
    "Mumbai Indians": [
      "PA Patel",
      "JC Buttler",
      "RG Sharma",
      "N Rana",
      "AT Rayudu",
      "KH Pandya",
      "KA Pollard",
      "HH Pandya",
      "TG Southee",
      "Harbhajan Singh",
      "MJ McClenaghan",
      "MG Johnson",
      "KV Sharma",
      "JJ Bumrah",
      "SL Malinga",
      "LMP Simmons",
      "SS Tiwary",
      "R Vinay Kumar"
    ],
    "Rising Pune Supergiant": [
      "AM Rahane",
      "MA Agarwal",
      "SPD Smith",
      "BA Stokes",
      "MS Dhoni",
      "MK Tiwary",
      "DT Christian",
      "F du Plessis",
      "RA Tripathi",
      "R Bhatia",
      "DL Chahar",
      "A Zampa",
      "AB Dinda",
      "Imran Tahir",
      "Ankit Sharma",
      "SN Thakur",
      "RD Chahar",
      "LH Ferguson",
      "JD Unadkat",
      "Washington Sundar"
    ],
    "Gujarat Lions": [
      "JJ Roy",
      "BB McCullum",
      "SK Raina",
      "AJ Finch",
      "KD Karthik",
      "DR Smith",
      "DS Kulkarni",
      "P Kumar",
      "Basil Thampi",
      "Ishan Kishan",
      "RA Jadeja",
      "AJ Tye",
      "JP Faulkner",
      "AD Nath",
      "IK Pathan",
      "Ankit Soni",
      "PJ Sangwan",
      "MM Patel",
      "MS Gony",
      "S Kaushik",
      "SB Jakati",
      "Tejas Baroka",
      "SS Agarwal",
      "NB Singh"
    ],
    "Kolkata Knight Riders": [
      "G Gambhir",
      "CA Lynn",
      "RV Uthappa",
      "MK Pandey",
      "YK Pathan",
      "SA Yadav",
      "CR Woakes",
      "SP Narine",
      "C de Grandhomme",
      "Shakib Al Hasan",
      "NM Coulter-Nile",
      "Kuldeep Yadav",
      "UT Yadav",
      "DM Bravo",
      "SP Jackson",
      "TA Boult",
      "IR Jaggi",
      "PP Chawla",
      "AS Rajpoot"
    ],
    "Kings XI Punjab": [
      "HM Amla",
      "M Vohra",
      "WP Saha",
      "AR Patel",
      "GJ Maxwell",
      "DA Miller",
      "MP Stoinis",
      "MM Sharma",
      "VR Aaron",
      "EJG Morgan",
      "KC Cariappa",
      "Sandeep Sharma",
      "I Sharma",
      "SE Marsh",
      "MJ Guptill",
      "Anureet Singh",
      "Swapnil Singh",
      "R Tewatia",
      "T Natarajan",
      "MJ Henry"
    ],
    "Delhi Daredevils": [
      "AP Tare",
      "SW Billings",
      "KK Nair",
      "SV Samson",
      "RR Pant",
      "CH Morris",
      "CR Brathwaite",
      "PJ Cummins",
      "A Mishra",
      "S Nadeem",
      "Z Khan",
      "CJ Anderson",
      "SS Iyer",
      "AD Mathews",
      "Mohammed Shami",
      "K Rabada",
      "AR Bawne",
      "MN Samuels",
      "J Yadav"
    ]
  },
  "2018": {
    "Mumbai Indians": [
      "RG Sharma",
      "E Lewis",
      "Ishan Kishan",
      "SA Yadav",
      "HH Pandya",
      "KH Pandya",
      "KA Pollard",
      "BCJ Cutting",
      "PJ Sangwan",
      "JJ Bumrah",
      "M Markande",
      "A Dananjaya",
      "MJ McClenaghan",
      "Mustafizur Rahman",
      "JP Duminy"
    ],
    "Chennai Super Kings": [
      "SR Watson",
      "AT Rayudu",
      "SK Raina",
      "MS Dhoni",
      "KM Jadhav",
      "RA Jadeja",
      "DJ Bravo",
      "DL Chahar",
      "Harbhajan Singh",
      "MA Wood",
      "Imran Tahir",
      "SW Billings",
      "M Vijay",
      "F du Plessis",
      "DR Shorey",
      "SN Thakur",
      "KV Sharma",
      "L Ngidi",
      "KM Asif",
      "DJ Willey"
    ],
    "Delhi Daredevils": [
      "C Munro",
      "G Gambhir",
      "SS Iyer",
      "V Shankar",
      "RR Pant",
      "R Tewatia",
      "CH Morris",
      "DT Christian",
      "GJ Maxwell",
      "JJ Roy",
      "Mohammed Shami",
      "S Nadeem",
      "TA Boult",
      "PP Shaw",
      "LE Plunkett",
      "A Mishra",
      "NV Ojha",
      "HV Patel",
      "Abhishek Sharma",
      "Avesh Khan",
      "S Lamichhane",
      "CJ Dala"
    ],
    "Kings XI Punjab": [
      "KL Rahul",
      "MA Agarwal",
      "Yuvraj Singh",
      "KK Nair",
      "DA Miller",
      "MP Stoinis",
      "AJ Finch",
      "AR Patel",
      "R Ashwin",
      "AJ Tye",
      "MM Sharma",
      "Mujeeb Ur Rahman",
      "CH Gayle",
      "BB Sran",
      "MK Tiwary",
      "AS Rajpoot",
      "AD Nath"
    ],
    "Royal Challengers Bangalore": [
      "BB McCullum",
      "Q de Kock",
      "V Kohli",
      "AB de Villiers",
      "Mandeep Singh",
      "SN Khan",
      "CR Woakes",
      "Washington Sundar",
      "P Negi",
      "CJ Anderson",
      "UT Yadav",
      "Mohammed Siraj",
      "M Vohra",
      "C de Grandhomme",
      "TG Southee",
      "PA Patel",
      "M Ashwin",
      "MM Ali",
      "YS Chahal",
      "K Khejroliya"
    ],
    "Kolkata Knight Riders": [
      "SP Narine",
      "CA Lynn",
      "RV Uthappa",
      "N Rana",
      "KD Karthik",
      "RK Singh",
      "AD Russell",
      "R Vinay Kumar",
      "TK Curran",
      "Shubman Gill",
      "Shivam Mavi",
      "MG Johnson",
      "PP Chawla",
      "Kuldeep Yadav",
      "M Prasidh Krishna",
      "JPR Scantlebury-Searles"
    ],
    "Rajasthan Royals": [
      "AM Rahane",
      "DJM Short",
      "SV Samson",
      "BA Stokes",
      "RA Tripathi",
      "JC Buttler",
      "K Gowtham",
      "S Gopal",
      "DS Kulkarni",
      "JD Unadkat",
      "B Laughlin",
      "H Klaasen",
      "STR Binny",
      "JC Archer",
      "MK Lomror",
      "P Chopra",
      "IS Sodhi",
      "Anureet Singh",
      "Ankit Sharma"
    ],
    "Sunrisers Hyderabad": [
      "WP Saha",
      "S Dhawan",
      "KS Williamson",
      "MK Pandey",
      "Shakib Al Hasan",
      "DJ Hooda",
      "YK Pathan",
      "Rashid Khan",
      "S Kaul",
      "Sandeep Sharma",
      "B Stanlake",
      "RK Bhui",
      "Mohammad Nabi",
      "Basil Thampi",
      "AD Hales",
      "B Kumar",
      "SP Goswami",
      "CR Brathwaite",
      "CJ Jordan",
      "KK Ahmed"
    ]
  },
  "2019": {
    "Royal Challengers Bangalore": [
      "V Kohli",
      "PA Patel",
      "MM Ali",
      "AB de Villiers",
      "SO Hetmyer",
      "S Dube",
      "C de Grandhomme",
      "Navdeep Saini",
      "YS Chahal",
      "UT Yadav",
      "Mohammed Siraj",
      "P Ray Barman",
      "MP Stoinis",
      "AD Nath",
      "TG Southee",
      "P Negi",
      "H Klaasen",
      "Gurkeerat Singh",
      "Washington Sundar",
      "DW Steyn",
      "K Khejroliya"
    ],
    "Chennai Super Kings": [
      "SR Watson",
      "AT Rayudu",
      "SK Raina",
      "KM Jadhav",
      "RA Jadeja",
      "MS Dhoni",
      "DJ Bravo",
      "DL Chahar",
      "SN Thakur",
      "MM Sharma",
      "F du Plessis",
      "MJ Santner",
      "SW Billings",
      "M Vijay",
      "DR Shorey",
      "Harbhajan Singh",
      "Imran Tahir",
      "SC Kuggeleijn",
      "KV Sharma"
    ],
    "Sunrisers Hyderabad": [
      "DA Warner",
      "JM Bairstow",
      "V Shankar",
      "YK Pathan",
      "MK Pandey",
      "KS Williamson",
      "Rashid Khan",
      "DJ Hooda",
      "Mohammad Nabi",
      "B Kumar",
      "Sandeep Sharma",
      "S Kaul",
      "RK Bhui",
      "Abhishek Sharma",
      "KK Ahmed",
      "Shakib Al Hasan",
      "WP Saha",
      "MJ Guptill",
      "Basil Thampi",
      "S Nadeem"
    ],
    "Kolkata Knight Riders": [
      "CA Lynn",
      "N Rana",
      "RV Uthappa",
      "KD Karthik",
      "AD Russell",
      "Shubman Gill",
      "SP Narine",
      "NS Naik",
      "PP Chawla",
      "Kuldeep Yadav",
      "M Prasidh Krishna",
      "HF Gurney",
      "JL Denly",
      "CR Brathwaite",
      "RK Singh",
      "Y Prithvi Raj",
      "KC Cariappa",
      "LH Ferguson",
      "S Sandeep Warrier"
    ],
    "Delhi Capitals": [
      "PP Shaw",
      "S Dhawan",
      "SS Iyer",
      "CA Ingram",
      "RR Pant",
      "KMA Paul",
      "AR Patel",
      "R Tewatia",
      "GH Vihari",
      "CH Morris",
      "HV Patel",
      "Avesh Khan",
      "K Rabada",
      "S Lamichhane",
      "C Munro",
      "A Mishra",
      "SE Rutherford",
      "J Suchith",
      "TA Boult",
      "I Sharma"
    ],
    "Mumbai Indians": [
      "RG Sharma",
      "Q de Kock",
      "SA Yadav",
      "KA Pollard",
      "Yuvraj Singh",
      "HH Pandya",
      "KH Pandya",
      "BCJ Cutting",
      "MJ McClenaghan",
      "Rasikh Salam",
      "M Markande",
      "JJ Bumrah",
      "Ishan Kishan",
      "RD Chahar",
      "SD Lad",
      "AS Joseph",
      "E Lewis",
      "BB Sran",
      "SL Malinga",
      "JP Behrendorff",
      "J Yadav",
      "AS Roy"
    ],
    "Kings XI Punjab": [
      "KL Rahul",
      "MA Agarwal",
      "CH Gayle",
      "SN Khan",
      "N Pooran",
      "Mandeep Singh",
      "DA Miller",
      "SM Curran",
      "GC Viljoen",
      "R Ashwin",
      "M Ashwin",
      "Mohammed Shami",
      "KK Nair",
      "Mujeeb Ur Rahman",
      "Harpreet Brar",
      "P Simran Singh",
      "AJ Tye",
      "AS Rajpoot",
      "CV Varun",
      "Arshdeep Singh"
    ],
    "Rajasthan Royals": [
      "AM Rahane",
      "JC Buttler",
      "SV Samson",
      "SPD Smith",
      "RA Tripathi",
      "BA Stokes",
      "K Gowtham",
      "JC Archer",
      "JD Unadkat",
      "S Gopal",
      "DS Kulkarni",
      "R Parag",
      "LS Livingstone",
      "AJ Turner",
      "STR Binny",
      "MK Lomror",
      "IS Sodhi",
      "VR Aaron",
      "S Midhun",
      "O Thomas"
    ]
  },
  "2020/21": {
    "Mumbai Indians": [
      "RG Sharma",
      "Q de Kock",
      "SA Yadav",
      "SS Tiwary",
      "HH Pandya",
      "KA Pollard",
      "KH Pandya",
      "JL Pattinson",
      "RD Chahar",
      "TA Boult",
      "JJ Bumrah",
      "Ishan Kishan",
      "NM Coulter-Nile",
      "DS Kulkarni",
      "J Yadav"
    ],
    "Chennai Super Kings": [
      "M Vijay",
      "SR Watson",
      "F du Plessis",
      "AT Rayudu",
      "RA Jadeja",
      "SM Curran",
      "MS Dhoni",
      "RD Gaikwad",
      "KM Jadhav",
      "N Jagadeesan",
      "DJ Bravo",
      "DL Chahar",
      "SN Thakur",
      "Imran Tahir",
      "L Ngidi",
      "PP Chawla",
      "JR Hazlewood",
      "KV Sharma",
      "Monu Kumar",
      "MJ Santner"
    ],
    "Delhi Capitals": [
      "PP Shaw",
      "S Dhawan",
      "SO Hetmyer",
      "SS Iyer",
      "RR Pant",
      "AR Patel",
      "MP Stoinis",
      "R Ashwin",
      "A Nortje",
      "K Rabada",
      "HV Patel",
      "AM Rahane",
      "AT Carey",
      "TU Deshpande",
      "P Dubey",
      "DR Sams",
      "MM Sharma",
      "Avesh Khan",
      "A Mishra",
      "I Sharma"
    ],
    "Kings XI Punjab": [
      "KL Rahul",
      "MA Agarwal",
      "KK Nair",
      "N Pooran",
      "GJ Maxwell",
      "SN Khan",
      "K Gowtham",
      "CJ Jordan",
      "JDS Neesham",
      "Ravi Bishnoi",
      "Mohammed Shami",
      "Mandeep Singh",
      "P Simran Singh",
      "Mujeeb Ur Rahman",
      "SS Cottrell",
      "Arshdeep Singh",
      "CH Gayle",
      "DJ Hooda",
      "M Ashwin",
      "Harpreet Brar"
    ],
    "Royal Challengers Bangalore": [
      "D Padikkal",
      "AJ Finch",
      "AB de Villiers",
      "V Kohli",
      "S Dube",
      "JR Philippe",
      "Washington Sundar",
      "UT Yadav",
      "Navdeep Saini",
      "DW Steyn",
      "YS Chahal",
      "MM Ali",
      "I Udana",
      "Mohammed Siraj",
      "CH Morris",
      "Gurkeerat Singh",
      "Shahbaz Ahmed",
      "A Zampa"
    ],
    "Sunrisers Hyderabad": [
      "DA Warner",
      "JM Bairstow",
      "MK Pandey",
      "PK Garg",
      "V Shankar",
      "Abhishek Sharma",
      "Rashid Khan",
      "B Kumar",
      "Sandeep Sharma",
      "MR Marsh",
      "T Natarajan",
      "WP Saha",
      "Mohammad Nabi",
      "KS Williamson",
      "Abdul Samad",
      "S Nadeem",
      "JO Holder",
      "KK Ahmed",
      "SP Goswami",
      "S Kaul",
      "Basil Thampi"
    ],
    "Rajasthan Royals": [
      "YBK Jaiswal",
      "SPD Smith",
      "SV Samson",
      "RV Uthappa",
      "R Tewatia",
      "R Parag",
      "TK Curran",
      "JC Archer",
      "JC Buttler",
      "S Gopal",
      "JD Unadkat",
      "AS Rajpoot",
      "MK Lomror",
      "AJ Tye",
      "Kartik Tyagi",
      "VR Aaron",
      "BA Stokes"
    ],
    "Kolkata Knight Riders": [
      "Shubman Gill",
      "SP Narine",
      "KD Karthik",
      "N Rana",
      "EJG Morgan",
      "AD Russell",
      "NS Naik",
      "PJ Cummins",
      "Shivam Mavi",
      "Kuldeep Yadav",
      "KL Nagarkoti",
      "RA Tripathi",
      "CV Varun",
      "T Banton",
      "M Prasidh Krishna",
      "LH Ferguson",
      "RK Singh",
      "S Sandeep Warrier",
      "CJ Green"
    ]
  },
  "2021": {
    "Mumbai Indians": [
      "RG Sharma",
      "CA Lynn",
      "SA Yadav",
      "Ishan Kishan",
      "HH Pandya",
      "KA Pollard",
      "KH Pandya",
      "M Jansen",
      "JJ Bumrah",
      "Q de Kock",
      "RD Chahar",
      "J Yadav",
      "TA Boult",
      "JDS Neesham",
      "Anmolpreet Singh",
      "SS Tiwary",
      "AF Milne",
      "NM Coulter-Nile",
      "PP Chawla",
      "DS Kulkarni"
    ],
    "Royal Challengers Bangalore": [
      "Washington Sundar",
      "V Kohli",
      "RM Patidar",
      "GJ Maxwell",
      "AB de Villiers",
      "Shahbaz Ahmed",
      "DT Christian",
      "KA Jamieson",
      "HV Patel",
      "Mohammed Siraj",
      "D Padikkal",
      "Navdeep Saini",
      "YS Chahal",
      "DR Sams",
      "KS Bharat",
      "Sachin Baby",
      "PWH de Silva",
      "TH David",
      "GHS Garton",
      "KW Richardson"
    ],
    "Chennai Super Kings": [
      "RD Gaikwad",
      "F du Plessis",
      "MM Ali",
      "SK Raina",
      "AT Rayudu",
      "RA Jadeja",
      "MS Dhoni",
      "SM Curran",
      "DJ Bravo",
      "SN Thakur",
      "DL Chahar",
      "RV Uthappa",
      "L Ngidi",
      "Imran Tahir",
      "JR Hazlewood",
      "KM Asif"
    ],
    "Delhi Capitals": [
      "PP Shaw",
      "S Dhawan",
      "RR Pant",
      "MP Stoinis",
      "AM Rahane",
      "Lalit Yadav",
      "TK Curran",
      "CR Woakes",
      "R Ashwin",
      "K Rabada",
      "SPD Smith",
      "SO Hetmyer",
      "SS Iyer",
      "AR Patel",
      "Avesh Khan",
      "RV Patel",
      "A Mishra",
      "LI Meriwala",
      "I Sharma",
      "A Nortje"
    ],
    "Kolkata Knight Riders": [
      "N Rana",
      "Shubman Gill",
      "RA Tripathi",
      "AD Russell",
      "EJG Morgan",
      "KD Karthik",
      "Shakib Al Hasan",
      "PJ Cummins",
      "Harbhajan Singh",
      "CV Varun",
      "SP Narine",
      "KL Nagarkoti",
      "M Prasidh Krishna",
      "Shivam Mavi",
      "VR Iyer",
      "TG Southee",
      "TL Seifert",
      "LH Ferguson",
      "S Sandeep Warrier"
    ],
    "Sunrisers Hyderabad": [
      "WP Saha",
      "DA Warner",
      "MK Pandey",
      "JM Bairstow",
      "Mohammad Nabi",
      "V Shankar",
      "Abdul Samad",
      "JO Holder",
      "Rashid Khan",
      "B Kumar",
      "S Nadeem",
      "Virat Singh",
      "Abhishek Sharma",
      "KK Ahmed",
      "Mujeeb Ur Rahman",
      "KS Williamson",
      "KM Jadhav",
      "J Suchith",
      "Sandeep Sharma",
      "JJ Roy",
      "PK Garg",
      "S Kaul",
      "T Natarajan",
      "Umran Malik"
    ],
    "Punjab Kings": [
      "KL Rahul",
      "MA Agarwal",
      "CH Gayle",
      "DJ Hooda",
      "N Pooran",
      "M Shahrukh Khan",
      "JA Richardson",
      "M Ashwin",
      "Mohammed Shami",
      "MC Henriques",
      "FA Allen",
      "Arshdeep Singh",
      "CJ Jordan",
      "Ravi Bishnoi",
      "P Simran Singh",
      "Harpreet Brar",
      "DJ Malan",
      "AK Markram",
      "NT Ellis",
      "Mandeep Singh",
      "SN Khan",
      "RP Meredith",
      "Jalaj S Saxena",
      "IC Porel",
      "AU Rashid"
    ],
    "Rajasthan Royals": [
      "BA Stokes",
      "SV Samson",
      "M Vohra",
      "JC Buttler",
      "S Dube",
      "R Parag",
      "R Tewatia",
      "CH Morris",
      "DA Miller",
      "JD Unadkat",
      "Mustafizur Rahman",
      "C Sakariya",
      "S Gopal",
      "YBK Jaiswal",
      "E Lewis",
      "LS Livingstone",
      "MK Lomror",
      "Kartik Tyagi",
      "T Shamsi",
      "GD Phillips",
      "K Yadav",
      "Anuj Rawat",
      "Akash Singh",
      "M Markande"
    ]
  },
  "2022": {
    "Chennai Super Kings": [
      "RD Gaikwad",
      "RV Uthappa",
      "DP Conway",
      "AT Rayudu",
      "RA Jadeja",
      "S Dube",
      "MS Dhoni",
      "MM Ali",
      "D Pretorius",
      "DJ Bravo",
      "CJ Jordan",
      "Mukesh Choudhary",
      "MJ Santner",
      "Simarjeet Singh",
      "M Theekshana",
      "N Jagadeesan",
      "TU Deshpande",
      "AF Milne",
      "PH Solanki",
      "M Pathirana"
    ],
    "Kolkata Knight Riders": [
      "AM Rahane",
      "VR Iyer",
      "N Rana",
      "SS Iyer",
      "SW Billings",
      "SP Jackson",
      "SP Narine",
      "AD Russell",
      "TG Southee",
      "UT Yadav",
      "CV Varun",
      "PJ Cummins",
      "Rasikh Salam",
      "AJ Finch",
      "Aman Hakim Khan",
      "Shivam Mavi",
      "RK Singh",
      "B Indrajith",
      "Harshit Rana",
      "AS Roy",
      "A Tomar"
    ],
    "Mumbai Indians": [
      "RG Sharma",
      "Ishan Kishan",
      "Anmolpreet Singh",
      "Tilak Varma",
      "KA Pollard",
      "TH David",
      "DR Sams",
      "M Ashwin",
      "JJ Bumrah",
      "D Brevis",
      "SA Yadav",
      "Ramandeep Singh",
      "JD Unadkat",
      "TS Mills",
      "FA Allen",
      "HR Shokeen",
      "K Kartikeya",
      "RP Meredith",
      "T Stubbs",
      "R Sanjay Yadav",
      "Basil Thampi",
      "M Markande"
    ],
    "Delhi Capitals": [
      "PP Shaw",
      "TL Seifert",
      "Mandeep Singh",
      "RR Pant",
      "Lalit Yadav",
      "R Powell",
      "SN Thakur",
      "AR Patel",
      "Kuldeep Yadav",
      "KK Ahmed",
      "Mustafizur Rahman",
      "DA Warner",
      "SN Khan",
      "MR Marsh",
      "KS Bharat",
      "RV Patel",
      "A Nortje",
      "KL Nagarkoti",
      "C Sakariya"
    ],
    "Royal Challengers Bangalore": [
      "F du Plessis",
      "Anuj Rawat",
      "V Kohli",
      "KD Karthik",
      "SE Rutherford",
      "DJ Willey",
      "Shahbaz Ahmed",
      "PWH de Silva",
      "HV Patel",
      "GJ Maxwell",
      "SS Prabhudessai",
      "Akash Deep",
      "Mohammed Siraj",
      "JR Hazlewood",
      "RM Patidar",
      "MK Lomror",
      "S Kaul"
    ],
    "Punjab Kings": [
      "MA Agarwal",
      "S Dhawan",
      "PBB Rajapaksa",
      "LS Livingstone",
      "RA Bawa",
      "M Shahrukh Khan",
      "OF Smith",
      "Harpreet Brar",
      "RD Chahar",
      "K Rabada",
      "Arshdeep Singh",
      "JM Sharma",
      "VG Arora",
      "JM Bairstow",
      "P Simran Singh",
      "NT Ellis",
      "R Dhawan",
      "PN Mankad",
      "Sandeep Sharma"
    ],
    "Lucknow Super Giants": [
      "KL Rahul",
      "E Lewis",
      "Q de Kock",
      "MK Pandey",
      "DJ Hooda",
      "A Badoni",
      "KH Pandya",
      "PVD Chameera",
      "JO Holder",
      "K Gowtham",
      "MP Stoinis",
      "Avesh Khan",
      "Ravi Bishnoi",
      "Mohsin Khan",
      "KS Sharma",
      "M Vohra",
      "AJ Tye"
    ],
    "Gujarat Titans": [
      "Shubman Gill",
      "V Shankar",
      "MS Wade",
      "HH Pandya",
      "DA Miller",
      "R Tewatia",
      "A Manohar",
      "Rashid Khan",
      "B Sai Sudharsan",
      "WP Saha",
      "AS Joseph",
      "LH Ferguson",
      "Yash Dayal",
      "PJ Sangwan",
      "Mohammed Shami",
      "VR Aaron",
      "DG Nalkande",
      "R Sai Kishore"
    ],
    "Rajasthan Royals": [
      "JC Buttler",
      "YBK Jaiswal",
      "SV Samson",
      "D Padikkal",
      "SO Hetmyer",
      "R Parag",
      "NM Coulter-Nile",
      "R Ashwin",
      "Navdeep Saini",
      "TA Boult",
      "HE van der Dussen",
      "JDS Neesham",
      "M Prasidh Krishna",
      "YS Chahal",
      "KR Sen",
      "KK Nair",
      "DJ Mitchell",
      "OC McCoy"
    ],
    "Sunrisers Hyderabad": [
      "KS Williamson",
      "Abhishek Sharma",
      "RA Tripathi",
      "N Pooran",
      "AK Markram",
      "Abdul Samad",
      "R Shepherd",
      "Washington Sundar",
      "B Kumar",
      "Umran Malik",
      "Shashank Singh",
      "M Jansen",
      "SA Abbott",
      "S Gopal",
      "Kartik Tyagi",
      "J Suchith",
      "Fazalhaq Farooqi",
      "PK Garg",
      "T Natarajan"
    ]
  },
  "2023": {
    "Chennai Super Kings": [
      "DP Conway",
      "RD Gaikwad",
      "MM Ali",
      "BA Stokes",
      "AT Rayudu",
      "S Dube",
      "RA Jadeja",
      "MS Dhoni",
      "MJ Santner",
      "AM Rahane",
      "DL Chahar",
      "TU Deshpande",
      "RS Hangargekar",
      "SSB Magala",
      "D Pretorius",
      "Akash Singh",
      "M Theekshana",
      "M Pathirana"
    ],
    "Gujarat Titans": [
      "WP Saha",
      "Shubman Gill",
      "B Sai Sudharsan",
      "HH Pandya",
      "V Shankar",
      "R Tewatia",
      "Rashid Khan",
      "DA Miller",
      "A Manohar",
      "Noor Ahmad",
      "AS Joseph",
      "MD Shanaka",
      "Mohammed Shami",
      "MM Sharma",
      "DG Nalkande",
      "J Little",
      "Yash Dayal",
      "J Yadav"
    ],
    "Punjab Kings": [
      "P Simran Singh",
      "S Dhawan",
      "PBB Rajapaksa",
      "JM Sharma",
      "Sikandar Raza",
      "SM Curran",
      "M Shahrukh Khan",
      "MW Short",
      "Harpreet Brar",
      "RD Chahar",
      "NT Ellis",
      "Mohit Rathee",
      "R Dhawan",
      "Atharva Taide",
      "Harpreet Singh",
      "K Rabada",
      "LS Livingstone",
      "Arshdeep Singh",
      "Gurnoor Brar"
    ],
    "Kolkata Knight Riders": [
      "Mandeep Singh",
      "Rahmanullah Gurbaz",
      "AS Roy",
      "VR Iyer",
      "N Rana",
      "RK Singh",
      "AD Russell",
      "SN Thakur",
      "SP Narine",
      "UT Yadav",
      "N Jagadeesan",
      "JJ Roy",
      "Liton Das",
      "CV Varun",
      "D Wiese",
      "Harshit Rana",
      "VG Arora",
      "TG Southee",
      "Suyash Sharma",
      "LH Ferguson",
      "K Khejroliya"
    ],
    "Lucknow Super Giants": [
      "KL Rahul",
      "KR Mayers",
      "DJ Hooda",
      "KH Pandya",
      "MP Stoinis",
      "N Pooran",
      "A Badoni",
      "K Gowtham",
      "MA Wood",
      "R Shepherd",
      "JD Unadkat",
      "Ravi Bishnoi",
      "Avesh Khan",
      "Yudhvir Singh",
      "A Mishra",
      "Naveen-ul-Haq",
      "M Vohra",
      "KS Sharma",
      "Q de Kock",
      "Swapnil Singh",
      "PN Mankad",
      "Mohsin Khan",
      "Yash Thakur"
    ],
    "Delhi Capitals": [
      "PP Shaw",
      "DA Warner",
      "MR Marsh",
      "SN Khan",
      "RR Rossouw",
      "R Powell",
      "Aman Hakim Khan",
      "AR Patel",
      "Kuldeep Yadav",
      "C Sakariya",
      "Mukesh Kumar",
      "Abishek Porel",
      "A Nortje",
      "MK Pandey",
      "Lalit Yadav",
      "YV Dhull",
      "Mustafizur Rahman",
      "PD Salt",
      "RV Patel",
      "I Sharma",
      "PK Garg",
      "P Dubey",
      "KK Ahmed"
    ],
    "Rajasthan Royals": [
      "YBK Jaiswal",
      "JC Buttler",
      "SV Samson",
      "D Padikkal",
      "R Parag",
      "SO Hetmyer",
      "R Ashwin",
      "Dhruv Jurel",
      "JO Holder",
      "A Zampa",
      "TA Boult",
      "Abdul Basith",
      "Sandeep Sharma",
      "JE Root",
      "KM Asif",
      "YS Chahal",
      "NA Saini",
      "M Ashwin",
      "KR Sen",
      "K Yadav",
      "OC McCoy",
      "Navdeep Saini"
    ],
    "Sunrisers Hyderabad": [
      "Abhishek Sharma",
      "RA Tripathi",
      "HC Brook",
      "MA Agarwal",
      "Washington Sundar",
      "GD Phillips",
      "Abdul Samad",
      "AU Rashid",
      "B Kumar",
      "Umran Malik",
      "Anmolpreet Singh",
      "AK Markram",
      "H Klaasen",
      "M Jansen",
      "M Markande",
      "AJ Hosein",
      "Sanvir Singh",
      "Fazalhaq Farooqi",
      "Vivrant Sharma",
      "T Natarajan",
      "Mayank Dagar",
      "Kartik Tyagi",
      "Nithish Kumar Reddy"
    ],
    "Mumbai Indians": [
      "RG Sharma",
      "Ishan Kishan",
      "C Green",
      "SA Yadav",
      "Tilak Varma",
      "N Wadhera",
      "TH David",
      "HR Shokeen",
      "Arshad Khan",
      "T Stubbs",
      "PP Chawla",
      "JC Archer",
      "Arjun Tendulkar",
      "JP Behrendorff",
      "RP Meredith",
      "Vishnu Vinod",
      "CJ Jordan",
      "K Kartikeya",
      "D Jansen",
      "Akash Madhwal",
      "R Goyal"
    ],
    "Royal Challengers Bangalore": [
      "V Kohli",
      "F du Plessis",
      "KD Karthik",
      "GJ Maxwell",
      "MG Bracewell",
      "HV Patel",
      "Shahbaz Ahmed",
      "Anuj Rawat",
      "DJ Willey",
      "KV Sharma",
      "Akash Deep",
      "MK Lomror",
      "SS Prabhudessai",
      "WD Parnell",
      "PWH de Silva",
      "Vijaykumar Vyshak",
      "Mohammed Siraj",
      "JR Hazlewood",
      "KM Jadhav",
      "RJW Topley",
      "H Sharma"
    ]
  },
  "2024": {
    "Royal Challengers Bengaluru": [
      "V Kohli",
      "F du Plessis",
      "RM Patidar",
      "GJ Maxwell",
      "C Green",
      "Anuj Rawat",
      "KD Karthik",
      "MK Lomror",
      "Mayank Dagar",
      "RJW Topley",
      "Mohammed Siraj",
      "Saurav Chauhan",
      "WG Jacks",
      "Vijaykumar Vyshak",
      "Akash Deep",
      "SS Prabhudessai",
      "KV Sharma",
      "LH Ferguson",
      "Swapnil Singh",
      "Yash Dayal",
      "AS Joseph",
      "H Sharma"
    ],
    "Chennai Super Kings": [
      "RD Gaikwad",
      "R Ravindra",
      "AM Rahane",
      "DJ Mitchell",
      "S Dube",
      "RA Jadeja",
      "Sameer Rizvi",
      "MS Dhoni",
      "MM Ali",
      "MJ Santner",
      "SN Thakur",
      "TU Deshpande",
      "RJ Gleeson",
      "DL Chahar",
      "M Theekshana",
      "Mustafizur Rahman",
      "M Pathirana",
      "Mukesh Choudhary",
      "Simarjeet Singh"
    ],
    "Delhi Capitals": [
      "DA Warner",
      "MR Marsh",
      "SD Hope",
      "RR Pant",
      "RK Bhui",
      "T Stubbs",
      "AR Patel",
      "Sumit Kumar",
      "Abishek Porel",
      "Kuldeep Yadav",
      "PP Shaw",
      "Rasikh Salam",
      "A Nortje",
      "I Sharma",
      "Lalit Yadav",
      "Kumar Kushagra",
      "JA Richardson",
      "J Fraser-McGurk",
      "Mukesh Kumar",
      "LB Williams",
      "Gulbadin Naib",
      "KK Ahmed"
    ],
    "Punjab Kings": [
      "S Dhawan",
      "JM Bairstow",
      "P Simran Singh",
      "SM Curran",
      "JM Sharma",
      "LS Livingstone",
      "Shashank Singh",
      "Harpreet Brar",
      "Sikandar Raza",
      "Ashutosh Sharma",
      "Atharva Taide",
      "RR Rossouw",
      "Harpreet Singh",
      "HV Patel",
      "K Rabada",
      "RD Chahar",
      "Arshdeep Singh",
      "Shivam Singh",
      "V Kaverappa",
      "NT Ellis",
      "R Dhawan"
    ],
    "Kolkata Knight Riders": [
      "PD Salt",
      "SP Narine",
      "VR Iyer",
      "SS Iyer",
      "N Rana",
      "Ramandeep Singh",
      "RK Singh",
      "AD Russell",
      "MA Starc",
      "A Raghuvanshi",
      "AS Roy",
      "VG Arora",
      "MK Pandey",
      "Rahmanullah Gurbaz",
      "Harshit Rana",
      "CV Varun",
      "Suyash Sharma",
      "PVD Chameera"
    ],
    "Sunrisers Hyderabad": [
      "MA Agarwal",
      "Abhishek Sharma",
      "RA Tripathi",
      "AK Markram",
      "H Klaasen",
      "Abdul Samad",
      "Shahbaz Ahmed",
      "M Jansen",
      "PJ Cummins",
      "TM Head",
      "Washington Sundar",
      "Nithish Kumar Reddy",
      "B Kumar",
      "JD Unadkat",
      "Anmolpreet Singh",
      "Sanvir Singh",
      "V Viyaskanth",
      "T Natarajan",
      "M Markande",
      "Umran Malik"
    ],
    "Rajasthan Royals": [
      "YBK Jaiswal",
      "JC Buttler",
      "SV Samson",
      "R Parag",
      "SO Hetmyer",
      "Dhruv Jurel",
      "R Ashwin",
      "SB Dubey",
      "Tanush Kotian",
      "R Powell",
      "KA Maharaj",
      "TA Boult",
      "D Ferreira",
      "Avesh Khan",
      "T Kohler-Cadmore",
      "N Burger",
      "YS Chahal",
      "Sandeep Sharma",
      "KR Sen"
    ],
    "Lucknow Super Giants": [
      "Q de Kock",
      "D Padikkal",
      "KL Rahul",
      "A Badoni",
      "DJ Hooda",
      "N Pooran",
      "MP Stoinis",
      "KH Pandya",
      "Ravi Bishnoi",
      "Mohsin Khan",
      "Arshad Khan",
      "Arshad Khan (2)",
      "AA Kulkarni",
      "AJ Turner",
      "Yudhvir Singh",
      "Naveen-ul-Haq",
      "Yash Thakur",
      "M Siddharth",
      "MP Yadav",
      "S Joseph",
      "MJ Henry",
      "A Mishra",
      "K Gowtham"
    ],
    "Gujarat Titans": [
      "WP Saha",
      "Shubman Gill",
      "B Sai Sudharsan",
      "Azmatullah Omarzai",
      "DA Miller",
      "V Shankar",
      "R Tewatia",
      "Rashid Khan",
      "UT Yadav",
      "SH Johnson",
      "KS Williamson",
      "BR Sharath",
      "DG Nalkande",
      "Noor Ahmad",
      "MS Wade",
      "A Manohar",
      "M Shahrukh Khan",
      "MM Sharma",
      "R Sai Kishore",
      "MJ Suthar",
      "S Sandeep Warrier",
      "J Little",
      "Kartik Tyagi"
    ],
    "Mumbai Indians": [
      "Ishan Kishan",
      "Naman Dhir",
      "RG Sharma",
      "D Brevis",
      "Tilak Varma",
      "TH David",
      "G Coetzee",
      "HH Pandya",
      "PP Chawla",
      "JJ Bumrah",
      "SZ Mulani",
      "R Shepherd",
      "Akash Madhwal",
      "SA Yadav",
      "Mohammad Nabi",
      "N Wadhera",
      "L Wood",
      "A Kamboj",
      "KT Maphaka",
      "S Gopal",
      "N Thushara",
      "Arjun Tendulkar"
    ]
  },
  "2025": {
    "Kolkata Knight Riders": [
      "Q de Kock",
      "AM Rahane",
      "SP Narine",
      "VR Iyer",
      "A Raghuvanshi",
      "RK Singh",
      "AD Russell",
      "Ramandeep Singh",
      "Harshit Rana",
      "SH Johnson",
      "MM Ali",
      "MK Pandey",
      "VG Arora",
      "Rahmanullah Gurbaz",
      "R Powell",
      "AS Roy",
      "CV Varun",
      "A Nortje",
      "C Sakariya"
    ],
    "Royal Challengers Bengaluru": [
      "PD Salt",
      "V Kohli",
      "D Padikkal",
      "RM Patidar",
      "LS Livingstone",
      "JM Sharma",
      "TH David",
      "KH Pandya",
      "B Kumar",
      "MS Bhandage",
      "Yash Dayal",
      "JR Hazlewood",
      "JG Bethell",
      "R Shepherd",
      "MA Agarwal",
      "L Ngidi",
      "Rasikh Salam",
      "Suyash Sharma",
      "N Thushara"
    ],
    "Sunrisers Hyderabad": [
      "Abhishek Sharma",
      "TM Head",
      "Ishan Kishan",
      "Nithish Kumar Reddy",
      "H Klaasen",
      "Aniket Verma",
      "A Manohar",
      "PJ Cummins",
      "HV Patel",
      "Mohammed Shami",
      "Simarjeet Singh",
      "PWA Mulder",
      "PHKD Mendis",
      "Atharva Taide",
      "A Zampa",
      "Zeeshan Ansari",
      "JD Unadkat",
      "E Malinga",
      "RD Chahar",
      "Harsh Dubey"
    ],
    "Rajasthan Royals": [
      "YBK Jaiswal",
      "SV Samson",
      "R Parag",
      "N Rana",
      "Dhruv Jurel",
      "SB Dubey",
      "SO Hetmyer",
      "JC Archer",
      "PWH de Silva",
      "M Theekshana",
      "TU Deshpande",
      "K Kartikeya",
      "Sandeep Sharma",
      "V Suryavanshi",
      "Fazalhaq Farooqi",
      "Akash Madhwal",
      "KS Rathore",
      "KT Maphaka",
      "Yudhvir Singh"
    ],
    "Mumbai Indians": [
      "RG Sharma",
      "WG Jacks",
      "RD Rickelton",
      "SA Yadav",
      "Tilak Varma",
      "R Minz",
      "Naman Dhir",
      "MJ Santner",
      "DL Chahar",
      "TA Boult",
      "PVSN Raju",
      "HH Pandya",
      "JJ Bumrah",
      "C Bosch",
      "KV Sharma",
      "JM Bairstow",
      "RA Bawa",
      "V Puthur",
      "Mujeeb Ur Rahman",
      "Ashwani Kumar",
      "RJ Gleeson",
      "RJW Topley"
    ],
    "Chennai Super Kings": [
      "R Ravindra",
      "RA Tripathi",
      "RD Gaikwad",
      "S Dube",
      "DJ Hooda",
      "SM Curran",
      "RA Jadeja",
      "MS Dhoni",
      "R Ashwin",
      "Noor Ahmad",
      "V Shankar",
      "J Overton",
      "DP Conway",
      "A Kamboj",
      "SK Rasheed",
      "A Mhatre",
      "D Brevis",
      "KK Ahmed",
      "Urvil Patel",
      "NT Ellis",
      "M Pathirana",
      "Mukesh Choudhary"
    ],
    "Lucknow Super Giants": [
      "AK Markram",
      "MR Marsh",
      "N Pooran",
      "RR Pant",
      "DA Miller",
      "A Badoni",
      "SN Thakur",
      "Shahbaz Ahmed",
      "Ravi Bishnoi",
      "Abdul Samad",
      "Avesh Khan",
      "Akash Deep",
      "Prince Yadav",
      "DS Rathi",
      "MP Breetzke",
      "M Siddharth",
      "MP Yadav",
      "Akash Singh",
      "W O'Rourke"
    ],
    "Delhi Capitals": [
      "J Fraser-McGurk",
      "F du Plessis",
      "Abishek Porel",
      "Sameer Rizvi",
      "AR Patel",
      "T Stubbs",
      "Ashutosh Sharma",
      "V Nigam",
      "MA Starc",
      "Kuldeep Yadav",
      "MM Sharma",
      "KL Rahul",
      "KK Nair",
      "D Ferreira",
      "PVD Chameera",
      "M Tiwari",
      "Mustafizur Rahman",
      "Sediqullah Atal",
      "Mukesh Kumar",
      "T Natarajan"
    ],
    "Punjab Kings": [
      "Priyansh Arya",
      "P Simran Singh",
      "SS Iyer",
      "Azmatullah Omarzai",
      "GJ Maxwell",
      "MP Stoinis",
      "Shashank Singh",
      "N Wadhera",
      "Suryansh Shedge",
      "M Jansen",
      "Arshdeep Singh",
      "LH Ferguson",
      "JP Inglis",
      "XC Bartlett",
      "MJ Owen",
      "Harpreet Brar",
      "Musheer Khan",
      "KA Jamieson",
      "YS Chahal",
      "Vijaykumar Vyshak",
      "Yash Thakur",
      "P Dubey"
    ],
    "Gujarat Titans": [
      "B Sai Sudharsan",
      "Shubman Gill",
      "JC Buttler",
      "SE Rutherford",
      "R Tewatia",
      "Arshad Khan",
      "M Shahrukh Khan",
      "K Rabada",
      "Rashid Khan",
      "R Sai Kishore",
      "Washington Sundar",
      "G Coetzee",
      "Mohammed Siraj",
      "BKG Mendis",
      "M Prasidh Krishna",
      "I Sharma",
      "K Khejroliya",
      "Karim Janat"
    ]
  },
  "2026": {
    "Sunrisers Hyderabad": [
      "TM Head",
      "Abhishek Sharma",
      "Ishan Kishan",
      "Nithish Kumar Reddy",
      "H Klaasen",
      "S Arora",
      "Aniket Verma",
      "Harsh Dubey",
      "HV Patel",
      "DA Payne",
      "JD Unadkat",
      "Shivang Kumar",
      "LS Livingstone",
      "E Malinga",
      "PP Hinge",
      "Sakib Hussain"
    ],
    "Royal Challengers Bengaluru": [
      "PD Salt",
      "D Padikkal",
      "V Kohli",
      "RM Patidar",
      "JM Sharma",
      "TH David",
      "KH Pandya",
      "R Shepherd",
      "VR Iyer",
      "B Kumar",
      "JA Duffy",
      "Abhinandan Singh",
      "Suyash Sharma",
      "JR Hazlewood",
      "Rasikh Salam"
    ],
    "Kolkata Knight Riders": [
      "AM Rahane",
      "FH Allen",
      "C Green",
      "A Raghuvanshi",
      "RK Singh",
      "Ramandeep Singh",
      "AS Roy",
      "SP Narine",
      "Kartik Tyagi",
      "VG Arora",
      "CV Varun",
      "R Powell",
      "B Muzarabani",
      "Navdeep Saini"
    ],
    "Mumbai Indians": [
      "RD Rickelton",
      "RG Sharma",
      "SA Yadav",
      "Tilak Varma",
      "HH Pandya",
      "Naman Dhir",
      "SE Rutherford",
      "MJ Santner",
      "C Bosch",
      "SN Thakur",
      "DL Chahar",
      "TA Boult",
      "JJ Bumrah",
      "Q de Kock",
      "AM Ghazanfar",
      "M Markande"
    ],
    "Chennai Super Kings": [
      "SV Samson",
      "RD Gaikwad",
      "A Mhatre",
      "SN Khan",
      "MW Short",
      "Kartik Sharma",
      "S Dube",
      "J Overton",
      "Noor Ahmad",
      "MJ Henry",
      "A Kamboj",
      "PR Veer",
      "D Brevis",
      "KK Ahmed",
      "RD Chahar",
      "AJ Hosein",
      "Gurjapneet Singh"
    ],
    "Rajasthan Royals": [
      "YBK Jaiswal",
      "V Suryavanshi",
      "Dhruv Jurel",
      "R Parag",
      "SO Hetmyer",
      "D Ferreira",
      "RA Jadeja",
      "JC Archer",
      "LG Pretorius",
      "TU Deshpande",
      "Ravi Bishnoi",
      "N Burger",
      "Brijesh Sharma",
      "Sandeep Sharma"
    ],
    "Gujarat Titans": [
      "B Sai Sudharsan",
      "Shubman Gill",
      "JC Buttler",
      "GD Phillips",
      "Washington Sundar",
      "M Shahrukh Khan",
      "R Tewatia",
      "Rashid Khan",
      "Kumar Kushagra",
      "K Rabada",
      "Ashok Sharma",
      "Mohammed Siraj",
      "M Prasidh Krishna"
    ],
    "Punjab Kings": [
      "Priyansh Arya",
      "C Connolly",
      "P Simran Singh",
      "SS Iyer",
      "N Wadhera",
      "Shashank Singh",
      "MP Stoinis",
      "M Jansen",
      "XC Bartlett",
      "Arshdeep Singh",
      "Vijaykumar Vyshak",
      "YS Chahal"
    ],
    "Lucknow Super Giants": [
      "MR Marsh",
      "RR Pant",
      "AK Markram",
      "A Badoni",
      "N Pooran",
      "Abdul Samad",
      "MD Choudhary",
      "Shahbaz Ahmed",
      "Mohammed Shami",
      "A Nortje",
      "Mohsin Khan",
      "Avesh Khan",
      "GF Linde",
      "DS Rathi",
      "Prince Yadav",
      "M Siddharth"
    ],
    "Delhi Capitals": [
      "KL Rahul",
      "N Rana",
      "P Nissanka",
      "Sameer Rizvi",
      "AR Patel",
      "T Stubbs",
      "DA Miller",
      "V Nigam",
      "Kuldeep Yadav",
      "Ashutosh Sharma",
      "Auqib Nabi",
      "L Ngidi",
      "T Natarajan",
      "Mukesh Kumar"
    ]
  }
}